{"lang":"tr","version":"2026.04.08","formatVersion":2,"generatedAt":"2026-04-08T17:45:59.791Z","sourcesUsed":["manual","wiktionary"],"entries":[{"e":"aç açına","k":2},{"e":"aç karnına","k":2},{"e":"adamına göre","k":2},{"e":"adı çıkmak","k":2},{"e":"afyonu patlamak","k":2},{"e":"ağaç olmak","k":2},{"e":"ağaç yaşken eğilir","k":2},{"e":"ağızdan ağıza","k":2},{"e":"ağzı kulaklarına varmak","k":2},{"e":"ağzına sıçmak","k":2},{"e":"ağzından kaçırmak","k":2},{"e":"ağzının payını vermek","k":2},{"e":"ağzıyla kuş tutmak","k":2},{"e":"aklıma gelmişken","k":2},{"e":"aklına gelmek","k":2},{"e":"aklını kaçırmak","k":2},{"e":"aklını peynir ekmekle yemek","k":2},{"e":"altına sıçmak","k":2},{"e":"ana vatan kan ağlamak","k":2},{"e":"anası ağlamak","k":2},{"e":"arada sırada","k":2},{"e":"araya girmek","k":2},{"e":"armut dalının dibine düşer","k":2},{"e":"aslan yattığı yerden belli olur","k":2},{"e":"ateşe körükle gitmek","k":2},{"e":"ateşi bol olsun","k":2},{"e":"ayağı yerden kesilmek","k":2},{"e":"ayağını çelmek","k":2},{"e":"ayağını yorganına göre uzat","k":2},{"e":"ayak uydurmak","k":2},{"e":"aynı bokun laciverti","k":2},{"e":"bal olan yerde sinek de olur","k":2},{"e":"balık kavağa çıkınca","k":2},{"e":"balta olmak","k":2},{"e":"baltayı taşa vurmak","k":2},{"e":"bam teli","k":2},{"e":"bardağı taşıran son damla","k":2},{"e":"bardaktan boşanırcasına yağmak","k":2},{"e":"baş göz olmak","k":2},{"e":"başa çıkmak","k":2},{"e":"başına gelmek","k":2},{"e":"başını ağrıtmak","k":2},{"e":"başka bir deyişle","k":3,"x":["Başka bir deyişle seçeneğimiz yok."]},{"e":"bata çıka","k":2},{"e":"bayram etmek","k":2},{"e":"bayram yapmak","k":2},{"e":"bel bağlamak","k":2},{"e":"beraber olmak","k":2},{"e":"beyin yıkamak","k":2},{"e":"beyin yormak","k":2},{"e":"bir avuç toprak olmak","k":2},{"e":"bir bardak suda fırtına koparmak","k":2},{"e":"bir elin nesi var iki elin sesi var","k":2},{"e":"bir taşla iki kuş vurmak","k":2},{"e":"bitmek bilmeyen","k":2},{"e":"bok atmak","k":2},{"e":"bok götürmek","k":2},{"e":"boka sarmak","k":2},{"e":"boku çıkmak","k":2},{"e":"bokunda boncuk bulmak","k":2},{"e":"bokunu çıkarmak","k":2},{"e":"boyun eğmek","k":2},{"e":"bu arada","k":2},{"e":"bu ne perhiz bu ne lahana turşusu","k":2},{"e":"burnu havada","k":2},{"e":"burnunu sokmak","k":2},{"e":"burun farkı","k":2},{"e":"burun kıvırmak","k":2},{"e":"büyük oynamak","k":2},{"e":"büyük söz söylemek","k":2},{"e":"cama çıkmak","k":2},{"e":"can alıcı","k":2},{"e":"can atmak","k":2},{"e":"can çekişmek","k":2},{"e":"can çıkar huy çıkmaz","k":2},{"e":"can pazarı","k":2},{"e":"can vermek","k":2},{"e":"canı çekmek","k":2},{"e":"canı çıkmak","k":2},{"e":"canı yanmak","k":2},{"e":"canla başla","k":2},{"e":"çamur atmak","k":2},{"e":"çantada keklik","k":2},{"e":"çaresine bakmak","k":2},{"e":"çığır açmak","k":2},{"e":"çıkmaz ayın son çarşambası","k":2},{"e":"çiçeği burnunda","k":2},{"e":"çocuk aldırmak","k":2},{"e":"çocuk işi","k":2},{"e":"çocuk oyuncağı","k":2},{"e":"çomak sokmak","k":2},{"e":"dağdan gelip bağdakini kovmak","k":2},{"e":"dalga geçmek","k":2},{"e":"dallandırıp budaklandırmak","k":2},{"e":"damlaya damlaya göl olur","k":2},{"e":"darısı başına","k":2},{"e":"davulun sesi uzaktan hoş gelir","k":2},{"e":"dayak yemek","k":2},{"e":"dereyi görmeden paçaları sıvamak","k":2},{"e":"deveye hendek atlatmak","k":2,"x":["Bu işi bitirmek deveye hendek atlatmak gibi."]},{"e":"dışa vurmak","k":2},{"e":"dikkate almak","k":1,"x":["Lütfen önerilerimi dikkate alın."]},{"e":"dile getirmek","k":2},{"e":"dilinde tüy bitmek","k":2},{"e":"diz boyu","k":2},{"e":"dört göz","k":2},{"e":"dört gözle beklemek","k":2},{"e":"dörtköşe olmak","k":2},{"e":"düşe kalka","k":2},{"e":"ecel şerbeti içmek","k":2},{"e":"ekmeğine yağ sürmek","k":2},{"e":"el altından","k":2},{"e":"el atmak","k":2},{"e":"el kaldırmak","k":2},{"e":"el koymak","k":2},{"e":"elden çıkmak","k":2},{"e":"ele almak","k":1,"x":["Bu konuyu yarın ele alalım."]},{"e":"ele vermek","k":2},{"e":"eli açık","k":2},{"e":"eli armut toplamak","k":2},{"e":"eli ayağı titremek","k":2},{"e":"elinden gelmek","k":2},{"e":"elmayla armut","k":2},{"e":"en azından","k":3,"x":["En azından denedik."]},{"e":"eninde sonunda","k":2},{"e":"ermeni gelini gibi kırıtmak","k":2},{"e":"eşi benzeri olmayan","k":2},{"e":"etekleri zil çalmak","k":2},{"e":"evsiz barksız","k":2},{"e":"fevt olmak","k":2},{"e":"fırça atmak","k":2},{"e":"fırça çekmek","k":2},{"e":"foyasını ortaya çıkarmak","k":2},{"e":"fransız kalmak","k":2},{"e":"geç olsun da güç olmasın","k":2},{"e":"göklere çıkarmak","k":2},{"e":"görmezden gelmek","k":2},{"e":"göt etmek","k":2},{"e":"götünü yırtmak","k":2},{"e":"göz açıp kapayıncaya kadar","k":2},{"e":"göz alıcı","k":2},{"e":"göz ardı etmek","k":2},{"e":"göz atmak","k":2},{"e":"göz boyamak","k":2},{"e":"göz devirmek","k":2},{"e":"göz dikmek","k":2},{"e":"göz gezdirmek","k":2},{"e":"göz göre göre","k":2},{"e":"göz koymak","k":2},{"e":"göz önünde bulundurmak","k":1,"x":["Bu faktörü göz önünde bulundurmalıyız."]},{"e":"göz önüne getirmek","k":2},{"e":"göz yummak","k":2},{"e":"gözden çıkarmak","k":2},{"e":"gözden geçirmek","k":2},{"e":"gözden kaçırmak","k":2},{"e":"gözden kaçmak","k":2},{"e":"göze batmak","k":2},{"e":"göze çarpmak","k":2},{"e":"gözleri dolmak","k":2},{"e":"gözü açık gitmek","k":2},{"e":"gözü doymak","k":2},{"e":"gözü dönmek","k":2},{"e":"gözü kara","k":2},{"e":"gözü tutmak","k":2},{"e":"gözüne batmak","k":2},{"e":"gözünü korkutmak","k":2},{"e":"haddini aşmak","k":2},{"e":"haddini bilmek","k":2},{"e":"hafife almak","k":2},{"e":"hakk'ın rahmetine kavuşmak","k":2},{"e":"hapı yutmak","k":2},{"e":"haşır neşir","k":2},{"e":"havlayan köpek ısırmaz","k":2},{"e":"havlu atmak","k":2},{"e":"hayata geçirmek","k":1,"x":["Bu planı hayata geçirmemiz gerekiyor."]},{"e":"hayran kalmak","k":2},{"e":"her koyun kendi bacağından asılır","k":2},{"e":"hesaba katmak","k":1,"x":["Tüm riskleri hesaba katmalıyız."]},{"e":"iç açmak","k":2},{"e":"iç çekmek","k":2},{"e":"içi açılmak","k":2},{"e":"içine doğmak","k":2},{"e":"içine kurt düşmek","k":2},{"e":"içine sıçmak","k":2},{"e":"iki lafın belini kırmak","k":2},{"e":"ilk göz ağrısı","k":2},{"e":"inceldiği yerden kopmak","k":2},{"e":"indi bindi","k":2},{"e":"inkâr etmek","k":2},{"e":"intikam soğuk yenen bir yemektir","k":2},{"e":"ipin ucunu kaçırmak","k":2},{"e":"iple çekmek","k":2},{"e":"itin götüne sokmak","k":2},{"e":"iyilik eden iyilik bulur","k":2},{"e":"kafa tutmak","k":2},{"e":"kanadı altında","k":2},{"e":"kanat açmak","k":2},{"e":"kanat germek","k":2},{"e":"kanı kaynamak","k":2},{"e":"kanını emmek","k":2},{"e":"kapı yapmak","k":2},{"e":"karar vermek","k":1,"x":["Bir karar verme zamanı geldi."]},{"e":"karşı gelmek","k":2},{"e":"karşı koymak","k":2},{"e":"kaşla göz arasında","k":2},{"e":"kazık atmak","k":2},{"e":"kazık yemek","k":2},{"e":"keçileri kaçırmak","k":2},{"e":"kefeni yırtmak","k":2},{"e":"kendinden geçmek","k":2},{"e":"kendine gelmek","k":2},{"e":"kıçına tekmeyi atmak","k":2},{"e":"kıçını yırtmak","k":2},{"e":"kırkyılda bir","k":2},{"e":"kırkyılın başı","k":2},{"e":"kıt kanaat","k":2},{"e":"kol kanat olmak","k":2},{"e":"komşu komşunun külüne muhtaçtır","k":2},{"e":"komşu komşunun tütününe muhtaçtır","k":2},{"e":"koynuna almak","k":2},{"e":"kökünü kazımak","k":2},{"e":"köstek olmak","k":2},{"e":"kulak asmak","k":2},{"e":"kulak kabartmak","k":2},{"e":"kulak kesilmek","k":2},{"e":"kulak misafiri olmak","k":2},{"e":"kulak tutmak","k":2},{"e":"kuş uçurtmamak","k":2},{"e":"kuyruğunu kısmak","k":2},{"e":"küplere binmek","k":2},{"e":"laf işitmek","k":2},{"e":"lafla peynir gemisi yürümez","k":2},{"e":"layığını bulmak","k":2},{"e":"maydanoz olmak","k":2},{"e":"maytap geçmek","k":2},{"e":"meydana gelmek","k":2},{"e":"mısır'daki sağır sultan bile duydu","k":2},{"e":"minareyi yaptırmayan yerden bitmiş sanır","k":2},{"e":"muz cumhuriyeti","k":2},{"e":"mürekkep yalamak","k":2},{"e":"ne ekersen onu biçersin","k":2},{"e":"ne var ne yok","k":2},{"e":"nokta koymak","k":2},{"e":"olan biten","k":2},{"e":"omuz atmak","k":2},{"e":"oralı olmak","k":2},{"e":"ortadan kaldırmak","k":2},{"e":"ortaya çıkarmak","k":2},{"e":"ortaya koymak","k":2},{"e":"orucu uykuya tutturmak","k":2},{"e":"oruç tutmak","k":2},{"e":"ödü kopmak","k":2},{"e":"ödü patlamak","k":2},{"e":"ölme eşeğim ölme","k":2},{"e":"önünde sonunda","k":2},{"e":"önünü açmak","k":2},{"e":"öte yandan","k":3,"x":["Öte yandan faydaları da göz ardı edilemez."]},{"e":"özü sözü bir","k":2},{"e":"paçayı kurtarmak","k":2},{"e":"perde arkası","k":2},{"e":"pireye kızıp yorgan yakmak","k":2},{"e":"pireyi deve yapmak","k":2},{"e":"pot kırmak","k":2},{"e":"püf noktası","k":2},{"e":"rahmetli olmak","k":2},{"e":"sabahın körü","k":2},{"e":"sabreden derviş muradına ermiş","k":2},{"e":"sadede gelmek","k":2},{"e":"salça olmak","k":2},{"e":"samanlıkta iğne","k":2},{"e":"sırası gelmişken","k":2},{"e":"sırra kadem basmak","k":2},{"e":"sineye çekmek","k":2},{"e":"son nefes","k":2},{"e":"sonuç olarak","k":3,"x":["Sonuç olarak proje ertelendi."]},{"e":"sorun nedir","k":2},{"e":"söz vermek","k":1,"x":["Sana söz veriyorum."]},{"e":"sözüm meclisten dışarı","k":2},{"e":"sözüm ona","k":2},{"e":"sütten çıkmış ak kaşık","k":2},{"e":"şehadet şerbetini içmek","k":2},{"e":"şeytan tırnağı","k":2},{"e":"şunun bunun","k":2},{"e":"tadı kaçmak","k":2},{"e":"tadında bırakmak","k":2},{"e":"tadını çıkarmak","k":2},{"e":"taklaya gelmek","k":2},{"e":"taş çıkarmak","k":2},{"e":"taş kesilmek","k":2},{"e":"taş koymak","k":2},{"e":"taş üstüne taş koymak","k":2,"x":["Artık taş üstüne taş koyma zamanı."]},{"e":"taş yerinde ağırdır","k":2},{"e":"taşak geçmek","k":2},{"e":"taşları yerli yerine oturtmak","k":2,"x":["Sonunda taşlar yerli yerine oturdu."]},{"e":"tavan yapmak","k":2},{"e":"tekkeyi bekleyen çorbayı içer","k":2},{"e":"tekme atmak","k":2},{"e":"tenceresini kaynatmak","k":2},{"e":"tepesine çıkarmak","k":2},{"e":"tereciye tere satmak","k":2},{"e":"toprağa vermek","k":2},{"e":"toprak olmak","k":2},{"e":"torbada keklik","k":2},{"e":"turp gibi","k":2},{"e":"tuvaletini yapmak","k":2},{"e":"tükürdüğünü yalamak","k":2},{"e":"tüyleri diken diken olmak","k":2},{"e":"tüyleri ürpermek","k":2},{"e":"ulu orta","k":2},{"e":"üzüm üzüme baka baka kararır","k":2},{"e":"vakit nakittir","k":2},{"e":"vatan millet meselesi","k":2},{"e":"volta atmak","k":2},{"e":"yaka paça","k":2},{"e":"yalancının mumu yatsıya kadar yanar","k":2},{"e":"yangına körükle gitmek","k":2},{"e":"yanıp tutuşmak","k":2},{"e":"yerden yere vurmak","k":2},{"e":"yerle bir etmek","k":2},{"e":"yeşil ışık yakmak","k":2},{"e":"yok pahasına","k":2},{"e":"yol açmak","k":2},{"e":"yola çıkmak","k":1,"x":["Sabah erken yola çıktık."]},{"e":"yolun açık olsun","k":2},{"e":"yorgan döşek yatmak","k":2},{"e":"yüce gönüllü","k":2},{"e":"yüreği ağzına gelmek","k":2},{"e":"yüreği yerinden oynamak","k":2},{"e":"yüz göz","k":2},{"e":"yüz karası","k":2},{"e":"yüz tutmak","k":2},{"e":"yüz yüze","k":2},{"e":"yüzü asık","k":2},{"e":"yüzüne gözüne bulaştırmak","k":2},{"e":"yüzüne vurmak","k":2},{"e":"züğürt tesellisi","k":2}]}